typically/__init__.py
typically/core.py
typically/doc.md
typically/py.typed
typically/wip/ft/__init__.py
typically/wip/io/__init__.py
typically/wip/it/__init__.py
typically/wip/py/__init__.py
typically-0.1.8.dist-info/METADATA
typically-0.1.8.dist-info/WHEEL
typically-0.1.8.dist-info/licenses/LICENSE
typically-0.1.8.dist-info/RECORD
