Metadata-Version: 2.4
Name: typically
Version: 0.1.8
Summary: (UNSTABLE) Collection of common types.
Author-email: Hart Traveller <ruling_fiction.0b@icloud.com>
License-Expression: MIT
License-File: LICENSE
Requires-Python: >=3.11
Requires-Dist: typing-extensions>=4.15.0
